django_statsd/__init__.py
django_statsd/celery_hooks.py
django_statsd/middleware.py
django_statsd/models.py
django_statsd/panel.py
django_statsd/plugins.py
django_statsd/tests.py
django_statsd/urls.py
django_statsd/views.py
django_statsd/clients/__init__.py
django_statsd/clients/log.py
django_statsd/clients/normal.py
django_statsd/clients/null.py
django_statsd/clients/toolbar.py
django_statsd/loggers/__init__.py
django_statsd/loggers/errors.py
django_statsd/management/__init__.py
django_statsd/management/commands/__init__.py
django_statsd/management/commands/statsd_ping.py
django_statsd/patches/__init__.py
django_statsd/patches/cache.py
django_statsd/patches/db.py
django_statsd/patches/utils.py
django_statsd/static/stick.js
django_statsd/templates/toolbar_statsd/statsd.html
django_statsd_unleashed-1.1.1.dist-info/LICENSE.rst
django_statsd_unleashed-1.1.1.dist-info/METADATA
django_statsd_unleashed-1.1.1.dist-info/WHEEL
django_statsd_unleashed-1.1.1.dist-info/top_level.txt
django_statsd_unleashed-1.1.1.dist-info/RECORD
