Metadata-Version: 2.1
Name: django-statsd-unleashed
Version: 1.1.1
Summary: Django interface with statsd
Home-page: https://github.com/vikingco/django-statsd
Author: Andy McKay
Author-email: andym@mozilla.com
Maintainer: Unleashed NV
Maintainer-email: operations@unleashed.be
License: BSD
Platform: UNKNOWN
Classifier: Intended Audience :: Developers
Classifier: Programming Language :: Python
Classifier: Programming Language :: Python :: 2.7
Classifier: Programming Language :: Python :: 3
Classifier: Programming Language :: Python :: 3.6
Classifier: Operating System :: OS Independent
Classifier: Environment :: Web Environment
Classifier: Framework :: Django
License-File: LICENSE.rst
Requires-Dist: django (>=1.8)
Requires-Dist: statsd (<3.3)
